{"ProjectBreakpoints":"{\"Value\":{\"Process/SIGE/Process/FiltroFecha&Municipio.xaml\":[],\"P6_TasaMunicipal.xaml\":[{\"ConditionalExpression\":null,\"ActionExpression\":null,\"ExpectedHitCounter\":null,\"ShouldContinueAfterAction\":false,\"IsEnabled\":true,\"ActivityIdRef\":\"ShouldStop_1\",\"ActivityId\":\"1.515\",\"ActivityName\":\"Should Stop\"}]}}","ProjectWatches":"{\"Value\":[]}","LibraryProjectSettings":"{\"IncludeSourcesByDefault\":true,\"UseCSharpCompiler\":false,\"DefaultActivitiesRootCategories\":[null]}","OpenedDocuments":"[\"Process/WebREC/Process/DatosSolicitud.xaml\",\"Process/WebREC/Process/DocumentosAnexos.xaml\",\"P6_TasaMunicipal.xaml\"]"}